asyn_fifo_design1_verilog/RTL/dpram.v
module dpram #(parameter n=5)(
input wclk, rclk,
input wen, ren,
input [n-2:0] raddr_g, waddr_g,
output [3:0] rdata,
input [3:0] wdata );

wire [n-2:0] raddr_b, waddr_b;
reg  [3:0] mem [0 : 2**(n-1) - 1];

genvar i;
generate 
  for ( i=0; i<n-1; i=i+1 ) begin : block1
assign raddr_b[i] = ^(raddr_g>>i);
assign waddr_b[i] = ^(waddr_g>>i);
end
endgenerate

always @ (posedge wclk) begin
if (wen)
mem[waddr_b] <= wdata;
end

assign rdata = mem[raddr_b];
endmodule

asyn_fifo_design1_verilog/RTL/synchronizer.v
module synchronizer ( 
clk, inp, sync_outp, resetn );

parameter n = 5;
input clk, resetn;
input [n-1:0] inp;
output [n-1:0] sync_outp;

reg [n-1:0] reg1, reg2;

assign sync_outp = reg2;

always @ (posedge clk, negedge resetn) begin
if ( !resetn ) begin
reg1 <= 0;
reg2 <= 0;
end
else begin
reg1 <= inp;
reg2 <= reg1;
end
end
endmodule

asyn_fifo_design1_verilog/RTL/rptr_handler.v
module rptr_handler #(parameter n=5)(
input clk, rresetn, rinc,
input [n-1:0] rq2_wptr,
output [n-2:0] raddr,
output [n-1:0] rptr,
output reg empty );

reg [n-1:0] gptr;
reg inv_msb;
wire [n-1:0] gptr_next, b1, b2;

assign rptr = gptr;
assign b2 = b1 + ( rinc & ~empty );
assign gptr_next = b2^(b2>>1);
assign raddr = {inv_msb, gptr[n-3:0]};

genvar i;
generate 
  for ( i=0; i<n; i=i+1 ) begin : block
assign b1[i] = ^(gptr>>i);
end
endgenerate

always @ (posedge clk, negedge rresetn) begin
if ( ~rresetn ) begin
gptr <= 0;
inv_msb <= 1'b0;
empty <= 1'b1;
end
else begin
gptr <= gptr_next;
inv_msb <= ^gptr_next[n-1:n-2];
empty <= ( gptr_next == rq2_wptr );
end
end
endmodule

asyn_fifo_design1_verilog/RTL/wptr_handler.v
module wptr_handler #(parameter n = 5)(
input clk,
input winc,
input wresetn,
input [n-1:0] wq2rptr,
output [n-2:0] wraddr,
output [n-1:0] wptr, 
output reg full );

reg [n-1:0] gptr;
reg inv_msb;
wire [n-1:0] gptr_next, b1, b2;

assign b2 = b1 + ( winc  & ~full );
assign gptr_next = b2^(b2>>1);
assign wraddr = {inv_msb, gptr[n-3:0]};
assign wptr = gptr;

genvar i;
generate 
  for ( i=0; i<n; i=i+1 ) begin : block
assign b1[i] = ^(gptr>>i);
end
endgenerate

always @ (posedge clk, negedge wresetn) begin
if ( !wresetn )
gptr <= 0;
else
gptr <= gptr_next;
end

always @ (posedge clk, negedge wresetn) begin
if ( !wresetn )
inv_msb <= 0;
else 
inv_msb <= ^gptr_next[n-1:n-2];
end

always @ (posedge clk, negedge wresetn) begin
if ( !wresetn )
full <= 0;
else
full <= ( gptr_next == {~wq2rptr[n-1:n-2], wq2rptr[n-3:0]} );
end
endmodule

Dual-Clock-Asynchronous-FIFO/async_fifo.v
module async_fifo #(parameter n=5)(
input wclk, rclk, winc, rinc, wresetn, rresetn,
input [3:0] wdata,
output [3:0] rdata,
output full, empty );

wire [n-1:0] wptr, rptr, wq2rptr, rq2wptr;
wire [n-2:0] waddr, raddr;

wptr_handler #(n) wptr_handler_1 ( .clk(wclk), .winc(winc), .wresetn(wresetn), .wq2rptr(wq2rptr), 
.wraddr(waddr), .wptr(wptr), .full(full) );

rptr_handler #(n) rptr_handler_1 ( .clk(rclk), .rinc(rinc), .rresetn(rresetn), .rq2_wptr(rq2wptr), 
.raddr(raddr), .rptr(rptr), .empty(empty) );

synchronizer #(n) synchronizer_wr_domain ( .clk(wclk), .inp(rptr), .sync_outp(wq2rptr), .resetn(wresetn) );

synchronizer #(n) synchronizer_r_domain ( .clk(rclk), .inp(wptr), .sync_outp(rq2wptr), .resetn(rresetn) );

dpram #(n) dpram_1 ( .wclk(wclk), .rclk(rclk), .wen(winc & ~full), .ren(rinc & ~empty), .raddr_g(raddr),
.waddr_g(waddr), .rdata(rdata), .wdata(wdata) );

endmodule

Dual-Clock-Asynchronous-FIFO/testbench.sv
// Code your testbench here
// or browse Examples
`timescale 1ns/1ps
`include "async_fifo.v"
`include "dpram.v"
`include "rptr_handler.v"
`include "wptr_handler.v"
`include "synchronizer.v"

module testbench;

reg wclk, rclk, winc, rinc, wresetn, rresetn;
reg [3:0] wdata;
wire[3:0] rdata;
wire full, empty;

async_fifo test ( .wclk(wclk), .rclk(rclk), .winc(winc), .rinc(rinc), .wresetn(wresetn), .rresetn(rresetn), 
.wdata(wdata), .rdata(rdata), .full(full), .empty(empty) );

initial begin
wclk = 1'b0;
rclk = 1'b0;
winc = 1'b0;
rinc = 1'b0;
wresetn = 1'b0;
rresetn = 1'b0;
end

always #10 wclk = ~wclk;
always #30 rclk = ~rclk;

initial begin
#9 wresetn = 1'b1;
end

initial begin
#9 rresetn = 1'b1;
end

initial begin
winc = 1'b1;
rinc = 1'b1;
end

initial begin
wdata = 4'd1;
#21 wdata = 4'd3; 
#21 wdata = 4'd5;
#21 wdata = 4'd7;
#21 wdata = 4'd9;
end
initial begin
  $dumpfile("dump.vcd"); // Creates the data file (must be named dump.vcd)
  $dumpvars(1);          // Records signals (1 = current module; 0 =modules)
end  
/*int op1;
op1 = $fopen("results.txt", "w"); // You can name this anything
$fdisplay(fd, "Data: %h", data);
$fclose(fd);
  */

initial #500 $stop;

endmodule

Dual-Clock-Asynchronous-FIFO/dump.vcd
$date
Tue Jan 13 09:52:58 2026
$end
$version
Riviera-PRO Version 2023.04.112.8911
$end
$timescale
1 ps
$end

$scope module testbench $end
$var wire 4 ! rdata [3:0] $end
$var wire 1 " full $end
$var wire 1 # empty $end
$var reg 1 $ wclk $end
$var reg 1 % rclk $end
$var reg 1 & winc $end
$var reg 1 ' rinc $end
$var reg 1 ( wresetn $end
$var reg 1 ) rresetn $end
$var reg 4 * wdata [3:0] $end
$upscope $end

$enddefinitions $end
$dumpvars
bx !
0"
1#
0$
0%
1&
1'
0(
0)
b1 *
$end
#9000
1(
1)
#10000
1$
b1 !
#20000
0$
#21000
b11 *
#30000
1%
1$
#40000
0$
#42000
b101 *
#50000
1$
#60000
0%
0$
#63000
b111 *
#70000
1$
#80000
0$
#84000
b1001 *
#90000
1%
1$
#100000
0$
#110000
1$
#120000
0%
0$
#130000
1$
#140000
0$
#150000
1%
1$
0#
#160000
0$
#170000
1$
#180000
0%
0$
#190000
1$
#200000
0$
#210000
1%
1$
b11 !
#220000
0$
#230000
1$
#240000
0%
0$
#250000
1$
#260000
0$
#270000
1%
1$
b101 !
#280000
0$
#290000
1$
#300000
0%
0$
#310000
1$
#320000
0$
#330000
1%
1$
b111 !
#340000
0$
#350000
1$
1"
#360000
0%
0$
#370000
1$
#380000
0$
#390000
1%
1$
0"
b1001 !
#400000
0$
#410000
1$
1"
#420000
0%
0$
#430000
1$
#440000
0$
#450000
1%
1$
0"
#460000
0$
#470000
1$
1"
